ntl/__init__.py
pyntl-0.0.0.dev0.dist-info/LICENSE
pyntl-0.0.0.dev0.dist-info/METADATA
pyntl-0.0.0.dev0.dist-info/WHEEL
pyntl-0.0.0.dev0.dist-info/top_level.txt
pyntl-0.0.0.dev0.dist-info/RECORD
