Metadata-Version: 2.1
Name: pyntl
Version: 0.0.0.dev0
Summary: pyntl
Home-page: https://github.com/initc3/pyntl
Author: Decentralized Systems Lab
License: UNKNOWN
Project-URL: Source, https://github.com/initc3/pyntl
Project-URL: Tracker, https://github.com/initc3/pyntl/issues
Platform: linux
Classifier: Development Status :: 1 - Planning
Classifier: Intended Audience :: Developers
Classifier: License :: OSI Approved :: GNU General Public License v3 (GPLv3)
Classifier: Operating System :: POSIX
Classifier: Programming Language :: Python :: 3
Classifier: Programming Language :: Python :: 3 :: Only
Classifier: Programming Language :: Python :: 3.6
Classifier: Programming Language :: Python :: 3.7
Classifier: Programming Language :: Python :: 3.8
Classifier: Programming Language :: Python :: 3.9
Classifier: Topic :: Utilities
License-File: LICENSE
